[{"viacod":1146,"inscrlig":"0030550040","numero":211.0},{"viacod":1146,"inscrlig":"0030540035","numero":63.0},{"viacod":1146,"inscrlig":"0031770105","numero":190.0},{"viacod":1146,"inscrlig":"0030560015","numero":259.0},{"viacod":1146,"inscrlig":"0030560010","numero":247.0},{"viacod":1146,"inscrlig":"0030560030","numero":295.0},{"viacod":1146,"inscrlig":"0030550020","numero":161.0},{"viacod":1146,"inscrlig":"0030550030","numero":185.0},{"viacod":1146,"inscrlig":"0031790150","numero":268.0},{"viacod":1146,"inscrlig":"0031790160","numero":256.0},{"viacod":1146,"inscrlig":"0031760200","numero":14.0},{"viacod":1146,"inscrlig":"0031760240","numero":38.0},{"viacod":1146,"inscrlig":"0030540020","numero":27.0},{"viacod":1146,"inscrlig":"0031770085","numero":170.0},{"viacod":1146,"inscrlig":"0031770065","numero":150.0},{"viacod":1146,"inscrlig":"0031770075","numero":160.0},{"viacod":1146,"inscrlig":"0030560040","numero":319.0},{"viacod":1146,"inscrlig":"0030550010","numero":137.0},{"viacod":1146,"inscrlig":"0031760280","numero":86.0},{"viacod":1146,"inscrlig":"0030540045","numero":87.0},{"viacod":1146,"inscrlig":"0030540025","numero":39.0},{"viacod":1146,"inscrlig":"0030560050","numero":343.0},{"viacod":1146,"inscrlig":"0031760230","numero":26.0},{"viacod":1146,"inscrlig":"0030560025","numero":283.0},{"viacod":1146,"inscrlig":"0030550015","numero":149.0},{"viacod":1146,"inscrlig":"0030540040","numero":75.0},{"viacod":1146,"inscrlig":"0030540050","numero":99.0},{"viacod":1146,"inscrlig":"0030560005","numero":235.0},{"viacod":1146,"inscrlig":"0031760270","numero":74.0},{"viacod":1146,"inscrlig":"0030560045","numero":331.0},{"viacod":1146,"inscrlig":"0030540030","numero":51.0},{"viacod":1146,"inscrlig":"0031770055","numero":140.0},{"viacod":1146,"inscrlig":"0030550045","numero":219.0},{"viacod":1146,"inscrlig":"0031760255","numero":50.0},{"viacod":1146,"inscrlig":"0030540010","numero":15.0},{"viacod":1146,"inscrlig":"0031770095","numero":180.0},{"viacod":1146,"inscrlig":"0030560020","numero":271.0},{"viacod":1146,"inscrlig":"0030550025","numero":175.0},{"viacod":1146,"inscrlig":"0030560035","numero":307.0},{"viacod":1146,"inscrlig":"0030550005","numero":125.0},{"viacod":1146,"inscrlig":"0030570300","numero":300.0},{"viacod":1146,"inscrlig":"0030550035","numero":197.0}]