[{"viacod":253,"inscrlig":"2021000218","numero":394.0},{"viacod":253,"inscrlig":"2020910756","numero":645.0},{"viacod":253,"inscrlig":"2020910833","numero":567.0},{"viacod":253,"inscrlig":"2020910972","numero":425.0},{"viacod":253,"inscrlig":"2020910812","numero":585.0},{"viacod":253,"inscrlig":"2020880503","numero":706.0},{"viacod":253,"inscrlig":"2020910705","numero":699.0},{"viacod":253,"inscrlig":"2020910902","numero":495.0},{"viacod":253,"inscrlig":"2020910823","numero":579.0},{"viacod":253,"inscrlig":"2020880449","numero":612.0},{"viacod":253,"inscrlig":"2021000228","numero":408.0},{"viacod":253,"inscrlig":"2020910694","numero":705.0},{"viacod":253,"inscrlig":"2020911123","numero":285.0},{"viacod":253,"inscrlig":"2020911145","numero":265.0},{"viacod":253,"inscrlig":"2020910797","numero":595.0},{"viacod":253,"inscrlig":"2020880502","numero":690.0},{"viacod":253,"inscrlig":"2021000158","numero":368.0},{"viacod":253,"inscrlig":"2021000208","numero":384.0},{"viacod":253,"inscrlig":"2020910912","numero":485.0},{"viacod":253,"inscrlig":"2020910862","numero":537.0},{"viacod":253,"inscrlig":"2020910685","numero":735.0},{"viacod":253,"inscrlig":"2020880309","numero":468.0},{"viacod":253,"inscrlig":"2020911165","numero":253.0},{"viacod":253,"inscrlig":"2020911093","numero":305.0},{"viacod":253,"inscrlig":"2020911083","numero":315.0},{"viacod":253,"inscrlig":"2020880440","numero":610.0},{"viacod":253,"inscrlig":"2020880420","numero":594.0},{"viacod":253,"inscrlig":"2021000198","numero":374.0},{"viacod":253,"inscrlig":"2020880498","numero":646.0},{"viacod":253,"inscrlig":"2020880499","numero":656.0},{"viacod":253,"inscrlig":"2020880329","numero":508.0},{"viacod":253,"inscrlig":"2020911004","numero":393.0},{"viacod":253,"inscrlig":"2020910787","numero":605.0},{"viacod":253,"inscrlig":"2020910882","numero":529.0},{"viacod":253,"inscrlig":"2020910765","numero":635.0},{"viacod":253,"inscrlig":"2020911024","numero":375.0},{"viacod":253,"inscrlig":"2020880389","numero":556.0},{"viacod":253,"inscrlig":"2020880338","numero":518.0},{"viacod":253,"inscrlig":"2020880247","numero":426.0},{"viacod":253,"inscrlig":"2020880500","numero":670.0},{"viacod":253,"inscrlig":"2021000108","numero":254.0},{"viacod":253,"inscrlig":"2020880319","numero":494.0},{"viacod":253,"inscrlig":"2020880358","numero":538.0},{"viacod":253,"inscrlig":"2020880258","numero":436.0},{"viacod":253,"inscrlig":"2020880504","numero":716.0},{"viacod":253,"inscrlig":"2020910953","numero":445.0},{"viacod":253,"inscrlig":"2020910853","numero":555.0},{"viacod":253,"inscrlig":"2020910932","numero":463.0},{"viacod":253,"inscrlig":"2020880268","numero":444.0},{"viacod":253,"inscrlig":"2020880501","numero":680.0},{"viacod":253,"inscrlig":"2020910715","numero":689.0},{"viacod":253,"inscrlig":"2020911014","numero":383.0},{"viacod":253,"inscrlig":"2020911073","numero":325.0},{"viacod":253,"inscrlig":"2020910943","numero":453.0},{"viacod":253,"inscrlig":"2020910984","numero":415.0},{"viacod":253,"inscrlig":"2020911054","numero":345.0},{"viacod":253,"inscrlig":"2020880348","numero":528.0},{"viacod":253,"inscrlig":"2020880439","numero":602.0},{"viacod":253,"inscrlig":"2021000118","numero":324.0},{"viacod":253,"inscrlig":"2021000115","numero":312.0},{"viacod":253,"inscrlig":"2020910994","numero":405.0},{"viacod":253,"inscrlig":"2020910725","numero":675.0},{"viacod":253,"inscrlig":"2020880238","numero":416.0},{"viacod":253,"inscrlig":"2020880459","numero":622.0},{"viacod":253,"inscrlig":"2020910857","numero":545.0},{"viacod":253,"inscrlig":"2021000112","numero":302.0},{"viacod":253,"inscrlig":"2020910775","numero":623.0},{"viacod":253,"inscrlig":"2020911034","numero":363.0},{"viacod":253,"inscrlig":"2020910745","numero":655.0},{"viacod":253,"inscrlig":"2020880563","numero":1709.0},{"viacod":253,"inscrlig":"2021000128","numero":334.0},{"viacod":253,"inscrlig":"2020880410","numero":582.0},{"viacod":253,"inscrlig":"2020880399","numero":568.0},{"viacod":253,"inscrlig":"2020911103","numero":293.0},{"viacod":253,"inscrlig":"2020910892","numero":505.0},{"viacod":253,"inscrlig":"2020910922","numero":475.0},{"viacod":253,"inscrlig":"2020880280","numero":454.0},{"viacod":253,"inscrlig":"2020910735","numero":661.0},{"viacod":253,"inscrlig":"2021000138","numero":346.0},{"viacod":253,"inscrlig":"2020911063","numero":333.0},{"viacod":253,"inscrlig":"2020910962","numero":435.0},{"viacod":253,"inscrlig":"2020880478","numero":636.0},{"viacod":253,"inscrlig":"2020880290","numero":464.0},{"viacod":253,"inscrlig":"2020880377","numero":548.0}]