[{"viacod":311,"inscrlig":"2020121000","numero":115.0},{"viacod":311,"inscrlig":"2020110821","numero":25.0},{"viacod":311,"inscrlig":"2020121024","numero":109.0},{"viacod":311,"inscrlig":"2020110543","numero":97.0},{"viacod":311,"inscrlig":"2020110846","numero":37.0},{"viacod":311,"inscrlig":"2020110584","numero":87.0},{"viacod":311,"inscrlig":"2020130069","numero":33.0},{"viacod":311,"inscrlig":"2020110536","numero":103.0},{"viacod":311,"inscrlig":"2020110843","numero":49.0},{"viacod":311,"inscrlig":"2020110888","numero":58.0}]