[{"viacod":705,"inscrlig":"2041620300","numero":547.0},{"viacod":705,"inscrlig":"2041610250","numero":403.0},{"viacod":705,"inscrlig":"2041630262","numero":698.0},{"viacod":705,"inscrlig":"2041630040","numero":428.0},{"viacod":705,"inscrlig":"2041600110","numero":34.0},{"viacod":705,"inscrlig":"2041610230","numero":427.0},{"viacod":705,"inscrlig":"2041620200","numero":669.0},{"viacod":705,"inscrlig":"2041600155","numero":205.0},{"viacod":705,"inscrlig":"2041630200","numero":628.0},{"viacod":705,"inscrlig":"2041630230","numero":662.0},{"viacod":705,"inscrlig":"2041620280","numero":571.0},{"viacod":705,"inscrlig":"2041620290","numero":563.0},{"viacod":705,"inscrlig":"2040581610","numero":128.0},{"viacod":705,"inscrlig":"2041610210","numero":451.0},{"viacod":705,"inscrlig":"2041610270","numero":379.0},{"viacod":705,"inscrlig":"2041600100","numero":20.0},{"viacod":705,"inscrlig":"2041630271","numero":716.0},{"viacod":705,"inscrlig":"2041630150","numero":560.0},{"viacod":705,"inscrlig":"2041630080","numero":476.0},{"viacod":705,"inscrlig":"2041630160","numero":582.0},{"viacod":705,"inscrlig":"2041630220","numero":650.0},{"viacod":705,"inscrlig":"2041620275","numero":581.0},{"viacod":705,"inscrlig":"2041630170","numero":594.0},{"viacod":705,"inscrlig":"2041630020","numero":404.0},{"viacod":705,"inscrlig":"2041630250","numero":682.0},{"viacod":705,"inscrlig":"2041620180","numero":693.0},{"viacod":705,"inscrlig":"2040581600","numero":140.0},{"viacod":705,"inscrlig":"2041610260","numero":391.0},{"viacod":705,"inscrlig":"2041610190","numero":475.0},{"viacod":705,"inscrlig":"2041610280","numero":367.0},{"viacod":705,"inscrlig":"2041630260","numero":690.0},{"viacod":705,"inscrlig":"2041630130","numero":536.0},{"viacod":705,"inscrlig":"2041630270","numero":706.0},{"viacod":705,"inscrlig":"2041630210","numero":640.0},{"viacod":705,"inscrlig":"2041630077","numero":470.0},{"viacod":705,"inscrlig":"2041630010","numero":392.0},{"viacod":705,"inscrlig":"2041600200","numero":189.0},{"viacod":705,"inscrlig":"2041610160","numero":511.0},{"viacod":705,"inscrlig":"2041630240","numero":670.0},{"viacod":705,"inscrlig":"2041620310","numero":535.0},{"viacod":705,"inscrlig":"2041620295","numero":551.0},{"viacod":705,"inscrlig":"2041610150","numero":523.0},{"viacod":705,"inscrlig":"2041620220","numero":647.0},{"viacod":705,"inscrlig":"2041620260","numero":603.0},{"viacod":705,"inscrlig":"2040580035","numero":50.0},{"viacod":705,"inscrlig":"2041630100","numero":498.0},{"viacod":705,"inscrlig":"2041630030","numero":416.0},{"viacod":705,"inscrlig":"2041620230","numero":639.0},{"viacod":705,"inscrlig":"2041610180","numero":487.0},{"viacod":705,"inscrlig":"2041630140","numero":548.0},{"viacod":705,"inscrlig":"2041630190","numero":616.0},{"viacod":705,"inscrlig":"2041630110","numero":512.0},{"viacod":705,"inscrlig":"2041630070","numero":464.0},{"viacod":705,"inscrlig":"2041630268","numero":704.0},{"viacod":705,"inscrlig":"2041620250","numero":615.0},{"viacod":705,"inscrlig":"2041620170","numero":705.0},{"viacod":705,"inscrlig":"2041620210","numero":657.0},{"viacod":705,"inscrlig":"2041630120","numero":522.0},{"viacod":705,"inscrlig":"2041630005","numero":370.0},{"viacod":705,"inscrlig":"2041620270","numero":591.0},{"viacod":705,"inscrlig":"2040581620","numero":116.0},{"viacod":705,"inscrlig":"2040580030","numero":32.0},{"viacod":705,"inscrlig":"2041610220","numero":439.0},{"viacod":705,"inscrlig":"2041630090","numero":488.0},{"viacod":705,"inscrlig":"2041630065","numero":452.0},{"viacod":705,"inscrlig":"2041630075","numero":458.0},{"viacod":705,"inscrlig":"2041801805","numero":220.0},{"viacod":705,"inscrlig":"2041600140","numero":225.0},{"viacod":705,"inscrlig":"2041600130","numero":235.0},{"viacod":705,"inscrlig":"2042070218","numero":765.0},{"viacod":705,"inscrlig":"2042070198","numero":726.0},{"viacod":705,"inscrlig":"2042070217","numero":760.0},{"viacod":705,"inscrlig":"2042070200","numero":40.0},{"viacod":705,"inscrlig":"2042070195","numero":715.0},{"viacod":705,"inscrlig":"2042070199","numero":739.0},{"viacod":705,"inscrlig":"2042070205","numero":735.0},{"viacod":705,"inscrlig":"2042070219","numero":761.0},{"viacod":705,"inscrlig":"2042070209","numero":741.0},{"viacod":705,"inscrlig":"2042070211","numero":757.0},{"viacod":705,"inscrlig":"2042070210","numero":745.0},{"viacod":705,"inscrlig":"2042070207","numero":736.0},{"viacod":705,"inscrlig":"2042070208","numero":746.0},{"viacod":705,"inscrlig":"2042070193","numero":60.0},{"viacod":705,"inscrlig":"2041610200","numero":463.0},{"viacod":705,"inscrlig":"2041630180","numero":604.0},{"viacod":705,"inscrlig":"2040580045","numero":66.0},{"viacod":705,"inscrlig":"2040581590","numero":156.0},{"viacod":705,"inscrlig":"2042070220","numero":755.0},{"viacod":705,"inscrlig":"2042070192","numero":57.0},{"viacod":705,"inscrlig":"2042070206","numero":55.0},{"viacod":705,"inscrlig":"2041610240","numero":415.0},{"viacod":705,"inscrlig":"2041600080","numero":249.0},{"viacod":705,"inscrlig":"2041630050","numero":440.0},{"viacod":705,"inscrlig":"2041630060","numero":448.0},{"viacod":705,"inscrlig":"2041620190","numero":681.0},{"viacod":705,"inscrlig":"2041620240","numero":627.0},{"viacod":705,"inscrlig":"2040580020","numero":22.0},{"viacod":705,"inscrlig":"2040581630","numero":100.0},{"viacod":705,"inscrlig":"2040580040","numero":60.0},{"viacod":705,"inscrlig":"2041610170","numero":499.0}]