[{"viacod":765,"inscrlig":"2140480137","numero":117.0},{"viacod":765,"inscrlig":"2140480045","numero":19.0},{"viacod":765,"inscrlig":"2140480172","numero":135.0},{"viacod":765,"inscrlig":"2140480217","numero":187.0},{"viacod":765,"inscrlig":"2140480122","numero":87.0},{"viacod":765,"inscrlig":"2140480103","numero":65.0},{"viacod":765,"inscrlig":"2140470327","numero":144.0},{"viacod":765,"inscrlig":"2140470379","numero":78.0},{"viacod":765,"inscrlig":"2140470294","numero":180.0},{"viacod":765,"inscrlig":"2140480274","numero":217.0},{"viacod":765,"inscrlig":"2140470455","numero":30.0},{"viacod":765,"inscrlig":"2140470425","numero":40.0},{"viacod":765,"inscrlig":"2140470297","numero":160.0},{"viacod":765,"inscrlig":"2140470399","numero":66.0},{"viacod":765,"inscrlig":"2140470363","numero":94.0},{"viacod":765,"inscrlig":"2140480353","numero":391.0},{"viacod":765,"inscrlig":"2140470337","numero":114.0},{"viacod":765,"inscrlig":"2140470415","numero":50.0},{"viacod":765,"inscrlig":"2140470347","numero":100.0},{"viacod":765,"inscrlig":"2140470276","numero":390.0},{"viacod":765,"inscrlig":"2140470367","numero":80.0},{"viacod":765,"inscrlig":"2140480062","numero":37.0},{"viacod":765,"inscrlig":"2140470473","numero":20.0},{"viacod":765,"inscrlig":"2140470500","numero":10.0}]