[{"viacod":771,"inscrlig":"2140410103","numero":23.0},{"viacod":771,"inscrlig":"2140440167","numero":170.0},{"viacod":771,"inscrlig":"2140410079","numero":57.0},{"viacod":771,"inscrlig":"2140402923","numero":428.0},{"viacod":771,"inscrlig":"2140402785","numero":208.0},{"viacod":771,"inscrlig":"2140491046","numero":355.0},{"viacod":771,"inscrlig":"2140490910","numero":725.0},{"viacod":771,"inscrlig":"2140472065","numero":233.0},{"viacod":771,"inscrlig":"2140472029","numero":193.0},{"viacod":771,"inscrlig":"2140472015","numero":175.0},{"viacod":771,"inscrlig":"2140470136","numero":139.0},{"viacod":771,"inscrlig":"2140501000","numero":500.0},{"viacod":771,"inscrlig":"2140491063","numero":393.0},{"viacod":771,"inscrlig":"2140491089","numero":388.0},{"viacod":771,"inscrlig":"2140491046","numero":350.0},{"viacod":771,"inscrlig":"2140492424","numero":245.0},{"viacod":771,"inscrlig":"2140410494","numero":115.0},{"viacod":771,"inscrlig":"2140410054","numero":99.0},{"viacod":771,"inscrlig":"2140430116","numero":86.0}]