[{"viacod":909,"inscrlig":"0054750100","numero":547.0},{"viacod":909,"inscrlig":"0051460260","numero":127.0},{"viacod":909,"inscrlig":"0051460220","numero":175.0},{"viacod":909,"inscrlig":"0051580090","numero":456.0},{"viacod":909,"inscrlig":"0051460280","numero":101.0},{"viacod":909,"inscrlig":"0051450285","numero":226.0},{"viacod":909,"inscrlig":"0054750090","numero":559.0},{"viacod":909,"inscrlig":"0051460190","numero":213.0},{"viacod":909,"inscrlig":"0051340040","numero":50.0},{"viacod":909,"inscrlig":"0051340050","numero":60.0},{"viacod":909,"inscrlig":"0051580030","numero":384.0},{"viacod":909,"inscrlig":"0051580100","numero":468.0},{"viacod":909,"inscrlig":"0051510190","numero":261.0},{"viacod":909,"inscrlig":"0051580140","numero":516.0},{"viacod":909,"inscrlig":"0051450200","numero":130.0},{"viacod":909,"inscrlig":"0051510170","numero":285.0},{"viacod":909,"inscrlig":"0051610210","numero":481.0},{"viacod":909,"inscrlig":"0051600180","numero":427.0},{"viacod":909,"inscrlig":"0051460180","numero":225.0},{"viacod":909,"inscrlig":"0051460240","numero":151.0},{"viacod":909,"inscrlig":"0051590160","numero":389.0},{"viacod":909,"inscrlig":"0051580155","numero":548.0},{"viacod":909,"inscrlig":"0051350145","numero":31.0},{"viacod":909,"inscrlig":"0051600160","numero":439.0},{"viacod":909,"inscrlig":"0051460230","numero":163.0},{"viacod":909,"inscrlig":"0051580120","numero":492.0},{"viacod":909,"inscrlig":"0051580160","numero":560.0},{"viacod":909,"inscrlig":"0051600170","numero":433.0},{"viacod":909,"inscrlig":"0051460250","numero":139.0},{"viacod":909,"inscrlig":"0051580080","numero":444.0},{"viacod":909,"inscrlig":"0051450180","numero":106.0},{"viacod":909,"inscrlig":"0051450210","numero":142.0},{"viacod":909,"inscrlig":"0051340060","numero":70.0},{"viacod":909,"inscrlig":"0051580110","numero":480.0},{"viacod":909,"inscrlig":"0051350105","numero":75.0},{"viacod":909,"inscrlig":"0051520210","numero":311.0},{"viacod":909,"inscrlig":"0051450260","numero":202.0},{"viacod":909,"inscrlig":"0051450220","numero":154.0},{"viacod":909,"inscrlig":"0051520195","numero":323.0},{"viacod":909,"inscrlig":"0051460200","numero":201.0},{"viacod":909,"inscrlig":"0051340030","numero":36.0},{"viacod":909,"inscrlig":"0051580070","numero":432.0},{"viacod":909,"inscrlig":"0051580050","numero":408.0},{"viacod":909,"inscrlig":"0051450270","numero":214.0},{"viacod":909,"inscrlig":"0051580040","numero":396.0},{"viacod":909,"inscrlig":"0051350115","numero":63.0},{"viacod":909,"inscrlig":"0051450240","numero":178.0},{"viacod":909,"inscrlig":"0051450230","numero":166.0},{"viacod":909,"inscrlig":"0051610220","numero":467.0},{"viacod":909,"inscrlig":"0051610190","numero":499.0},{"viacod":909,"inscrlig":"0051460170","numero":237.0},{"viacod":909,"inscrlig":"0051450190","numero":118.0},{"viacod":909,"inscrlig":"0051460270","numero":115.0},{"viacod":909,"inscrlig":"0051460210","numero":189.0},{"viacod":909,"inscrlig":"0051350125","numero":55.0},{"viacod":909,"inscrlig":"0051590150","numero":373.0},{"viacod":909,"inscrlig":"0051450250","numero":190.0},{"viacod":909,"inscrlig":"0051580150","numero":536.0},{"viacod":909,"inscrlig":"0051610165","numero":515.0},{"viacod":909,"inscrlig":"0051340020","numero":24.0},{"viacod":909,"inscrlig":"0051590170","numero":403.0},{"viacod":909,"inscrlig":"0051340070","numero":82.0},{"viacod":909,"inscrlig":"0051580145","numero":524.0},{"viacod":909,"inscrlig":"0051580060","numero":420.0},{"viacod":909,"inscrlig":"0051350135","numero":43.0},{"viacod":909,"inscrlig":"0051580130","numero":504.0},{"viacod":909,"inscrlig":"0051510180","numero":273.0},{"viacod":909,"inscrlig":"0051520180","numero":335.0}]