[{"viacod":936,"inscrlig":"0054820360","numero":7.0},{"viacod":936,"inscrlig":"0054820260","numero":83.0},{"viacod":936,"inscrlig":"0054820300","numero":53.0},{"viacod":936,"inscrlig":"0054830020","numero":16.0},{"viacod":936,"inscrlig":"0054820330","numero":29.0},{"viacod":936,"inscrlig":"0054820270","numero":75.0},{"viacod":936,"inscrlig":"0054820250","numero":89.0},{"viacod":936,"inscrlig":"0054830010","numero":8.0},{"viacod":936,"inscrlig":"0054820340","numero":21.0},{"viacod":936,"inscrlig":"0054820290","numero":61.0},{"viacod":936,"inscrlig":"0054840010","numero":70.0},{"viacod":936,"inscrlig":"0054820350","numero":15.0},{"viacod":936,"inscrlig":"0054820320","numero":37.0},{"viacod":936,"inscrlig":"0054820280","numero":69.0},{"viacod":936,"inscrlig":"0054820310","numero":45.0}]