[{"viacod":974,"inscrlig":"0053870070","numero":297.0},{"viacod":974,"inscrlig":"0053920020","numero":329.0},{"viacod":974,"inscrlig":"0053920030","numero":315.0},{"viacod":974,"inscrlig":"0053740170","numero":193.0},{"viacod":974,"inscrlig":"0052590410","numero":310.0},{"viacod":974,"inscrlig":"0053740270","numero":79.0},{"viacod":974,"inscrlig":"0053740200","numero":139.0},{"viacod":974,"inscrlig":"0052590440","numero":280.0},{"viacod":974,"inscrlig":"0053740190","numero":169.0},{"viacod":974,"inscrlig":"0053740240","numero":109.0},{"viacod":974,"inscrlig":"0052590280","numero":374.0},{"viacod":974,"inscrlig":"0052590290","numero":364.0},{"viacod":974,"inscrlig":"0052590180","numero":416.0},{"viacod":974,"inscrlig":"0052590230","numero":404.0},{"viacod":974,"inscrlig":"0053860080","numero":243.0},{"viacod":974,"inscrlig":"0053740250","numero":99.0},{"viacod":974,"inscrlig":"0052590170","numero":420.0},{"viacod":974,"inscrlig":"0052590310","numero":354.0},{"viacod":974,"inscrlig":"0052590340","numero":344.0},{"viacod":974,"inscrlig":"0053740180","numero":179.0},{"viacod":974,"inscrlig":"0053740230","numero":119.0},{"viacod":974,"inscrlig":"0052590350","numero":338.0},{"viacod":974,"inscrlig":"0053920010","numero":343.0},{"viacod":974,"inscrlig":"0052590140","numero":440.0},{"viacod":974,"inscrlig":"0053860100","numero":217.0},{"viacod":974,"inscrlig":"0053740290","numero":59.0},{"viacod":974,"inscrlig":"0052590380","numero":334.0},{"viacod":974,"inscrlig":"0052590400","numero":316.0},{"viacod":974,"inscrlig":"0053740260","numero":89.0},{"viacod":974,"inscrlig":"0052590360","numero":336.0},{"viacod":974,"inscrlig":"0052590300","numero":358.0},{"viacod":974,"inscrlig":"0052590370","numero":330.0},{"viacod":974,"inscrlig":"0053870060","numero":311.0},{"viacod":974,"inscrlig":"0053740210","numero":139.0},{"viacod":974,"inscrlig":"0053740220","numero":129.0},{"viacod":974,"inscrlig":"0053740280","numero":69.0},{"viacod":974,"inscrlig":"0052590450","numero":270.0},{"viacod":974,"inscrlig":"0052590390","numero":320.0},{"viacod":974,"inscrlig":"0053860090","numero":229.0},{"viacod":974,"inscrlig":"0052590150","numero":434.0},{"viacod":974,"inscrlig":"0052590430","numero":290.0},{"viacod":974,"inscrlig":"0052590420","numero":300.0},{"viacod":974,"inscrlig":"0052590240","numero":394.0},{"viacod":974,"inscrlig":"0052590270","numero":98.0},{"viacod":974,"inscrlig":"0052590460","numero":260.0},{"viacod":974,"inscrlig":"0052590320","numero":348.0},{"viacod":974,"inscrlig":"0052590260","numero":384.0},{"viacod":974,"inscrlig":"0052590160","numero":430.0}]